sigma/__init__.py
sigma/configuration.py
sigma/filter.py
sigma/merge_sigma.py
sigma/output.py
sigma/sigma-similarity.py
sigma/sigma-uuid.py
sigma/sigma2attack.py
sigma/sigma2genericsigma.py
sigma/sigma2misp.py
sigma/sigma_configurations_check.py
sigma/sigma_similarity.py
sigma/sigma_uuid.py
sigma/sigmac.py
sigma/tools.py
sigma/backends/ala.py
sigma/backends/arcsight.py
sigma/backends/athena.py
sigma/backends/base.py
sigma/backends/carbonblack.py
sigma/backends/chronicle.py
sigma/backends/cim.py
sigma/backends/csharp.py
sigma/backends/data.py
sigma/backends/datadog.py
sigma/backends/devo.py
sigma/backends/discovery.py
sigma/backends/dnif.py
sigma/backends/ee-outliers.py
sigma/backends/elasticsearch.py
sigma/backends/exceptions.py
sigma/backends/fireeye-helix.py
sigma/backends/fortisiem.py
sigma/backends/graylog.py
sigma/backends/hawk.py
sigma/backends/hedera.py
sigma/backends/humio.py
sigma/backends/lacework.py
sigma/backends/limacharlie.py
sigma/backends/logiq.py
sigma/backends/logpoint.py
sigma/backends/mdatp.py
sigma/backends/misc.py
sigma/backends/mixins.py
sigma/backends/netwitness-epl.py
sigma/backends/netwitness.py
sigma/backends/opensearch.py
sigma/backends/powershell.py
sigma/backends/qradar.py
sigma/backends/qualys.py
sigma/backends/splunk.py
sigma/backends/splunkdm.py
sigma/backends/sql.py
sigma/backends/sqlite.py
sigma/backends/stix.py
sigma/backends/streamalert.py
sigma/backends/sumologic.py
sigma/backends/sysmon.py
sigma/backends/tools.py
sigma/backends/uberagent.py
sigma/config/collection.py
sigma/config/eventdict.py
sigma/config/exceptions.py
sigma/config/mapping.py
sigma/parser/base.py
sigma/parser/collection.py
sigma/parser/condition.py
sigma/parser/exceptions.py
sigma/parser/rule.py
sigma/parser/modifiers/__init__.py
sigma/parser/modifiers/base.py
sigma/parser/modifiers/discovery.py
sigma/parser/modifiers/exceptions.py
sigma/parser/modifiers/mixins.py
sigma/parser/modifiers/transform.py
sigma/parser/modifiers/type.py
sigmatools-0.22.1.dist-info/LICENSE.LGPL.txt
sigmatools-0.22.1.dist-info/METADATA
sigmatools-0.22.1.dist-info/WHEEL
sigmatools-0.22.1.dist-info/entry_points.txt
sigmatools-0.22.1.dist-info/top_level.txt
sigmatools-0.22.1.dist-info/RECORD
