Metadata-Version: 2.1
Name: sigmatools
Version: 0.22.1
Summary: Tools for the Generic Signature Format for SIEM Systems
Home-page: https://github.com/Neo23x0/sigma
Author: Sigma Project
Author-email: thomas@patzke.org
License: LGPLv3
Keywords: security monitoring siem logging signatures elasticsearch splunk ids sysmon
Platform: UNKNOWN
Classifier: Development Status :: 5 - Production/Stable
Classifier: Intended Audience :: Developers
Classifier: Intended Audience :: Information Technology
Classifier: Intended Audience :: System Administrators
Classifier: Topic :: Security
Classifier: Topic :: Internet :: Log Analysis
Classifier: License :: OSI Approved :: GNU Lesser General Public License v3 (LGPLv3)
Classifier: Programming Language :: Python :: 3.8
Classifier: Programming Language :: Python :: 3.9
Classifier: Environment :: Console
Requires-Python: ~=3.8
Requires-Dist: PyYAML
Requires-Dist: pymisp
Requires-Dist: progressbar2
Requires-Dist: ruamel.yaml
Provides-Extra: test
Requires-Dist: coverage ; extra == 'test'
Requires-Dist: yamllint ; extra == 'test'
Requires-Dist: attackcti ; extra == 'test'
